README.md
setup.cfg
setup.py
domainer/__init__.py
domainer/cli.py
domainer/constants.py
domainer/domain.py
domainer/server.py
domainer/subdomain.py
domainer/version.py
domainer.egg-info/PKG-INFO
domainer.egg-info/SOURCES.txt
domainer.egg-info/dependency_links.txt
domainer.egg-info/entry_points.txt
domainer.egg-info/requires.txt
domainer.egg-info/top_level.txt
domainer/layers/__init__.py
domainer/layers/application/__init__.py
domainer/layers/application/controller.py
domainer/layers/application/logger.py
domainer/layers/application/commands/__init__.py
domainer/layers/application/commands/bus.py
domainer/layers/application/commands/command.py
domainer/layers/application/commands/handler.py
domainer/layers/application/events/__init__.py
domainer/layers/application/events/dispatcher.py
domainer/layers/application/events/event.py
domainer/layers/application/events/listener.py
domainer/layers/data/__init__.py
domainer/layers/data/daos/__init__.py
domainer/layers/data/daos/relational.py
domainer/layers/data/daos/document/__init__.py
domainer/layers/data/daos/document/base.py
domainer/layers/data/daos/document/elasticsearch.py
domainer/layers/data/daos/key_value/__init__.py
domainer/layers/data/daos/key_value/base.py
domainer/layers/data/daos/key_value/redis.py
domainer/layers/data/repositories/__init__.py
domainer/layers/data/repositories/base.py