Metadata-Version: 1.1
Name: domainer
Version: 0.0.1
Summary: A simple and intuitive Domain Driven Design (DDD) framework for Python, with CRUD operations for SQL and NoSQL databases.
Home-page: https://github.com/dutradda/domainer
Author: Diogo Dutra
Author-email: dutradda@gmail.com
License: MIT
Keywords: ddd domain-driven-design design-patterns software-architecture openapi oai swagger rest api crud api-first orm sqlalchemy redis elasticsearch
Platform: UNKNOWN
Classifier: License :: OSI Approved :: MIT License
Classifier: Programming Language :: Python
Classifier: Programming Language :: Python :: 2.7
Classifier: Programming Language :: Python :: 3.4
Classifier: Programming Language :: Python :: 3.5
Classifier: Programming Language :: Python :: 3.6
Classifier: Development Status :: 3 - Alpha
Classifier: Intended Audience :: Developers
Classifier: Operating System :: OS Independent
Classifier: Topic :: Internet :: WWW/HTTP
Classifier: Topic :: Software Development :: Libraries :: Python Modules
Classifier: Topic :: Utilities
Classifier: Topic :: Text Processing
Classifier: Topic :: Database :: Front-Ends
Classifier: Topic :: Software Development :: Libraries :: Python Modules
